src/__init__.py
src/cli.py
python_regrex-0.1.18.dist-info/METADATA
python_regrex-0.1.18.dist-info/WHEEL
python_regrex-0.1.18.dist-info/entry_points.txt
python_regrex-0.1.18.dist-info/RECORD
