Metadata-Version: 2.1
Name: python-regrex
Version: 0.1.18
Summary: string generator based on regex pattern
Home-page: https://github.com/morisono/regrex
Author: admin
Requires-Python: >=3.10,<4.0
Classifier: Programming Language :: Python :: 3
Classifier: Programming Language :: Python :: 3.10
Classifier: Programming Language :: Python :: 3.11
Classifier: Programming Language :: Python :: 3.12
Requires-Dist: aiofiles (==23.2.1)
Requires-Dist: aiohttp (==3.8.4)
Requires-Dist: exrex (==0.11.0)
Requires-Dist: httpx (==0.26.0)
Requires-Dist: natsort (>=8.4.0,<9.0.0)
Requires-Dist: pyyaml (==6.0.1)
Requires-Dist: tqdm (==4.66.1)
Project-URL: Repository, https://github.com/morisono/regrex
